pyenvertechevt800/__init__.py
pyenvertechevt800-0.2.4.dist-info/licenses/LICENSE
pyenvertechevt800-0.2.4.dist-info/METADATA
pyenvertechevt800-0.2.4.dist-info/WHEEL
pyenvertechevt800-0.2.4.dist-info/top_level.txt
pyenvertechevt800-0.2.4.dist-info/zip-safe
pyenvertechevt800-0.2.4.dist-info/RECORD
