Metadata-Version: 2.4
Name: pyenvertechevt800
Version: 0.2.4
Summary: Library to interface an Envertech EVT-800 device
Home-page: https://github.com/daniel-bergmann-00/pyenvertech-evt800
Download-URL: https://github.com/daniel-bergmann-00/pyenvertech-evt800/tarball/0.2.4
Author: Daniel Bergmann
Author-email: daniel.bergmann00+envertec_evt800@gmail.com
License: MIT
Requires-Python: >=3.9
License-File: LICENSE
Dynamic: author
Dynamic: author-email
Dynamic: description
Dynamic: description-content-type
Dynamic: download-url
Dynamic: home-page
Dynamic: license
Dynamic: license-file
Dynamic: requires-python
Dynamic: summary
